{"description": "My place is close to Brooklyn Bridge, New York Stock Exchange, Wall St., Financial District. You\u2019ll love my place because of the location, the people, the ambiance, the neighborhood, and the outdoors space. My place is good for couples, solo adventurers, and business travelers.", "name": "Luxury Studio Downtown Manhattan", "picture_url": "https://a0.muscache.com/im/pictures/4bd50666-5f34-4ec7-8653-f294d4d81a5e.jpg?aki_policy=large", "url": "airbnb.com/rooms/15919536", "id": "15919536", "price": 200}